{"_id":"000000000000000000000000","pid":{"page-no":800231,"frame-id":"g"},"visible":true,"header-text":"","cost":0,"disable-clear":false,"frame-type":"","redirect":{"page-no":0,"frame-id":""},"content":{"data":"|A|Gg|IF|3E|2X|3@|0(|2QR|0L^,|4I|1H|5P|0V|4I|1I|5P|08|4I|1J|5P|1Y|4I|1K|5P|0'|4I|L|5P|1^|4I|1L|5P|07|4I|1Q|5P|0O|4I|1T|5P|0K|4I|1^|5P|0.`|5F|2K|3E|2K|4I|1X|4P|1D|3I|1@|2EK|0`|3I|1@|2EL|0`|4F|2K|1PD|3I|1W|2EK|0`|5F|2L|3E|2L|4I|0(|4P|5I|3I|1@|2EL|0LC,L|4^|0,}|1C|0-|2ELEK|0`|4F|2L|1PL|3I|0'|2EL|4F|2K|1PD|3I|1W|2EK|0``|3F|2L|3D|2K|3I|1^|0}|5T_@|0(|3P|1[|4@|1Y|3P|1W|4J|00|1H|3I|1I|0}|5T_|0L|2[|0,|2H|00|1H|3I|1J|0}|5T_|0L|3F|0,`}a)|1@|3D|2K|3B|0(}|4\\|0)|3B|1@|3@|1D|0L|1C|0*|3B|0(|3D|2K|0}|4\\|0)|3F|2L|3@|1@|0}|1C|0*|3B|1@|3@|1D|0}|1C|0*|2FRDS|0`|3I|1L|0}|5T_|3I|1@|2ELEK|3I|0}|3B|1@|2]|1@D|2]|1@E|2]|1@F|5H|4P|5T|3B|1@|2]|1@G|5H@H|4P|5X|3@|1W|3I|1@|2Y|1@|4X|2H|1P|5Z|0`|3I|2XE|3@I|1@|2E|3A|0Lt*`|3I|1@|2E|3@I|2XE|3A|0Lt*`|3I|1@|2E|3@I|1D|2E|3AI|1X|2E|3BI|4X|2E|3CI|5H|2E|3DI|1C|2E|3E|0LJ*|3I|1X|2E|3@I|4X|2E|3AI|1@|2E|3BI|1D|2E|3CI|5H|2E|3DI|1C|2E|3E|0L)*|Z047","type":"rawV"},"footer":{"data":"","type":"","merge-data":null},"title":{"data":"","type":"","merge-data":null},"routing-table":[8002310,8002311,8002312,8002313,8002314,8002315,8002316,8002317,8002318,8002319,80023],"connection":{"address":"","mode":"","port":0},"author-id":"","response-data":{"response-fields":null,"response-action":{"exec":"","args":null,"post-action-frame":{"page-no":0,"frame-id":""},"post-cancel-frame":{"page-no":0,"frame-id":""}}},"cursor":false,"navmessage-select":"","navmessage-notfound":""}